README.md
requirements.txt
requirements_test.txt
setup.cfg
setup.py
src/dictionaryfield/__init__.py
src/dictionaryfield/extras.py
src/dictionaryfield/fields.py
src/dictionaryfield/widgets.py
src/dictionaryfield/templates/dictionaryfield/row.html
src/dictionaryfield/templates/dictionaryfield/widget.html
src/dictionaryfield/templatetags/__init__.py
src/dictionaryfield/templatetags/dictionary_tags.py
src/django_dictionaryfield.egg-info/PKG-INFO
src/django_dictionaryfield.egg-info/SOURCES.txt
src/django_dictionaryfield.egg-info/dependency_links.txt
src/django_dictionaryfield.egg-info/not-zip-safe
src/django_dictionaryfield.egg-info/requires.txt
src/django_dictionaryfield.egg-info/top_level.txt