Metadata-Version: 1.0
Name: django-dictionaryfield
Version: 1.0
Summary: Dynamic list of inputs
Home-page: https://bitbucket.ncbi.nlm.nih.gov/projects/PMC/repos/django-dictionaryfield/browse
Author: UNKNOWN
Author-email: misiurev@ncbi.nlm.nih.gov
License: Public Domain
Platform: UNKNOWN
